testthing.py
test_thing-0.4.0.dist-info/entry_points.txt
test_thing-0.4.0.dist-info/licenses/COPYING
test_thing-0.4.0.dist-info/WHEEL
test_thing-0.4.0.dist-info/METADATA
test_thing-0.4.0.dist-info/RECORD
