Metadata-Version: 2.4
Name: test.thing
Version: 0.4.0
Summary: A simple modern VM runner
Requires-Python: >= 3.12
License-Expression: GPL-3.0-or-later
License-File: COPYING
Project-URL: Source, https://codeberg.org/lis/test.thing
